{
  "lorem": {
    "base": "Lorem ipsum dolor sit amet, consectetur adipisicing elit. Debitis, quis optio perspiciatis. Doloribus maxime nam, nobis error molestiae. Distinctio facere omnis repellat hic perspiciatis aliquid vel voluptas quae optio porro?",
    "long": "Lorem ipsum dolor sit amet, consectetur adipisicing elit. Assumenda veniam consequatur perferendis hic harum sit odit fuga, quam delectus quos at quibusdam eveniet fugit molestiae, optio qui quis totam dolorem.Quos quis accusantium eos provident vitae, illo tenetur fuga voluptatibus odio, maxime odit vel cum dolore ipsam consequuntur vero unde. Et non obcaecati aliquid autem! Delectus pariatur, totam error est.Laudantium perferendis, voluptate officia illo repudiandae corporis. Unde veritatis doloribus quod neque eum, accusamus sit quae consequatur nostrum autem, architecto quis, nesciunt magni rerum exercitationem? Optio est veniam at error.",
    "short": "Lorem ipsum dolor sit amet, consectetur adipisicing elit.",
    "tiny": "Lorem ipsum dolor"
  },
  "input": {
    "type": "text",
    "placeholder": "Name",
    "name": "name",
    "required": true,
    "value": ""
  },
  "select": {
    "placeholder": "Select your job",
    "required": true,
    "name": "job",
    "options": [{
      "value": "1",
      "text": "Frontend Dev"
    }, {
      "value": "2",
      "text": "Backend Dev"
    }, {
      "value": "3",
      "text": "UX Designer"
    }, {
      "value": "4",
      "text": "SEO Specialist"
    }]
  },
  "checkbox": {
    "required": true,
    "name": "privacy",
    "checked": false,
    "text": "Lorem ipsum dolor sit amet, consectetur adipisicing elit. Repellendus beatae ad saepe sapiente minus odit excepturi veritatis quam quae modi sed perferendis nostrum pariatur, dolorem accusantium, illo iste qui blanditiis."
  },
  "radio": {
    "required": true,
    "name": "privacy",
    "checked": false,
    "text": "Lorem ipsum dolor sit amet, consectetur adipisicing elit. Repellendus beatae ad saepe sapiente minus odit excepturi veritatis quam quae modi sed perferendis nostrum pariatur, dolorem accusantium, illo iste qui blanditiis."
  },
  "textarea": {
    "placeholder": "Message",
    "name": "message",
    "required": true
  },
  "button": {
    "href": "#",
    "text": "Lorem Ipsum",
    "is_anchor": true
  },
  "images": {
    "fullscreen": "http://placehold.it/1920x1080",
    "16x9": "http://placehold.it/1280x720",
    "4x3": "http://placehold.it/1024x768",
    "square": "http://placehold.it/800x800",
    "1920": "http://placehold.it/1920x1080",
    "1280": "http://placehold.it/1280x720",
    "1024": "http://placehold.it/1024x576",
    "720": "http://placehold.it/720x405",
    "640": "http://placehold.it/640x360"
  },
  "bgs": {
    "1280": "http://placehold.it/1280x720",
    "1024": "http://placehold.it/1024x576",
    "720": "http://placehold.it/720x405",
    "640": "http://placehold.it/640x360"
  },
  "button-icon": {
    "href": "#",
    "icon": "play",
    "text": "Play Video"
  },
  "button-link": {
    "href": "#",
    "icon": "plus",
    "text": "Lorem Ipsum"
  },
  "button-cta": {
    "href": "#",
    "icon": "cart",
    "text": "Shop online"
  },
  "preview": {
    "href": "#",
    "image": {
      "1024": "http://placehold.it/1024x576",
      "720": "http://placehold.it/720x405",
      "640": "http://placehold.it/640x360"
    },
    "title": "Tibetan Culture Week Arcidosso, Italy",
    "description": "Lorem ipsum dolor sit amet, consectetur adipisicing elit. Sequi nobis voluptas officia delectus, laudantium dicta id mollitia, vero maiores consequatur odio alias! Illum repellat repudiandae sint facere natus. Tenetur, eos.",
    "button-icon": {
      "icon": "camera",
      "text": "Open Gallery"
    },
    "gallery-list": [
      {
        "src": "http://68.media.tumblr.com/ef71091b57992c63cd6b6371160694b7/tumblr_o9c283SMGZ1st5lhmo1_1280.jpg",
        "subHtml": "Lorem ipsum dolor sit amet, consectetur adipisicing elit. Quod enim est libero dolorum quam ut, reprehenderit nisi quae, quos placeat explicabo beatae praesentium eos modi quas minus magnam sed soluta."
      },
      {
        "src": "http://68.media.tumblr.com/4fcf20d7631aff0d2a24d0ce3a956d9f/tumblr_o9c2s3dCQL1st5lhmo1_1280.jpg",
        "subHtml": "Lorem ipsum dolor sit amet, consectetur adipisicing elit. A, tenetur, sint. Odio possimus deleniti sequi excepturi fugiat, molestias amet fuga vel neque, perferendis totam? Dolorum dolore beatae, magnam asperiores libero!"
      },
      {
        "src": "http://68.media.tumblr.com/bb94d05f5881bcc4b8e100818135a86c/tumblr_o9hc6qTj5Q1st5lhmo1_1280.jpg",
        "subHtml": "Lorem ipsum dolor sit amet, consectetur adipisicing elit. Doloribus voluptatibus expedita alias distinctio quas! Autem magni quasi in distinctio totam odit! Praesentium quam illum, tempora voluptate eum necessitatibus, molestiae numquam."
      },
      {
        "src": "http://68.media.tumblr.com/1c231fa8526a2f47e557109e8b307899/tumblr_o8pumfyDR11st5lhmo1_1280.jpg",
        "subHtml": "Lorem ipsum dolor sit amet, consectetur adipisicing elit. Accusantium, officiis? Molestiae recusandae quia ad corporis, omnis doloribus perferendis consectetur iure, quasi nobis a enim praesentium. Esse incidunt deserunt sint et!"
      },
      {
        "src": "http://68.media.tumblr.com/b7355206f8ad142d3a50d722baa1c11d/tumblr_o8pudm4Y0S1st5lhmo1_1280.jpg",
        "subHtml": "Lorem ipsum dolor sit amet, consectetur adipisicing elit. Atque perferendis sapiente cumque eos commodi ipsam nemo vero. Iste debitis assumenda dolores, perspiciatis illum nostrum eum, totam ipsum minima id at."
      }
    ]
  },
  "nav-group": {
    "head": {
      "href": "#",
      "text": "Lorem ipsum dolor"
    },
    "list": [
      {
        "href": "#",
        "text": "Lorem",
        "has_children": true,
        "children": [
          { "href": "#", "text": "Ipsum" },
          { "href": "#", "text": "Dolor" },
          { "href": "#", "text": "Consectetur" },
          { "href": "#", "text": "Adipisicing" }
        ]
      },
      { "href": "#", "text": "Ipsum" },
      { "href": "#", "text": "Dolor" },
      { "href": "#", "text": "Consectetur" },
      { "href": "#", "text": "Adipisicing" }
    ]
  },
  "panel": {
    "body": "<h3>Lorem ipsum dolor sit amet</h3><p>Lorem ipsum dolor sit amet, consectetur adipisicing elit. Mollitia commodi sequi <a href=\"#\">libero explicabo consequuntur</a> ad, delectus optio magnam, facere molestias perspiciatis, pariatur eveniet? Modi expedita nisi sit, placeat voluptatem natus.</p>",
    "button-link": {
      "href": "#",
      "icon": "plus",
      "text": "Read More"
    }
  },
  "media": {
    "href": "#",
    "image": "http://placehold.it/490x480",
    "body": "<h2><a href=\"#\">Lorem ipsum dolor sit amet consectetur adipisicing elit.</a></h2><p>Lorem ipsum dolor sit amet, consectetur adipisicing elit. Mollitia commodi sequi <a href=\"#\">libero explicabo consequuntur</a> ad, delectus optio magnam, facere molestias perspiciatis, pariatur eveniet? Modi expedita nisi sit, placeat voluptatem natus.</p>",
    "button-icon": {
      "href": "#",
      "icon": "link",
      "text": "Read More"
    }
  },
  "carousel": {
    "title": "Lorem ipsum dolor sit amet",
    "next": {
      "button-icon": {
        "href": "#",
        "icon": "arrow-right8",
        "text": ""
      }
    },
    "prev": {
      "button-icon": {
        "href": "#",
        "icon": "arrow-left8",
        "text": ""
      }
    }
  },
  "media-list":[[],[],[],[]],
  "card": {
    "href": "#",
    "image": "http://placehold.it/630x400",
    "tags": [
      { "href": "#", "text": "yoga" },
      { "href": "#", "text": "lorem ipsum" },
      { "href": "#", "text": "yoga" },
      { "href": "#", "text": "lorem ipsum" },
      { "href": "#", "text": "yoga" },
      { "href": "#", "text": "lorem ipsum" }
    ],
    "body": "<h3><a href=\"#\">Lorem ipsum west Lorem ipsum west</a></h3><p>Lorem ipsum west Lorem ipsum west Lorem ipsum west Lorem ipsum west</p>",
    "footer": "<h3>Lorem ipsum west Lorem ipsum west</h3><p>from FRIDAY 07 SEPTEMBER 2016 <br>to TUESDAY 11 SEPTEMBER 2016</p>"
  },
  "card-event": {
    "card": {
      "href": "#",
      "image": "http://placehold.it/630x400",
      "body": "<h3><a href=\"#\">Loremss ipsum west Lorem ipsum west</a></h3>",
      "footer": "<a href=\"#\">1 Upcoming events</a>"
    }
  },
  "card-list": {
    "columns": "col-xs-12 col-sm-6 col-md-4 col-lg-3",
    "items": [[],[],[],[],[],[],[],[],[],[],[],[]]
  },
  "card-event-list": {
    "columns": "col-xs-12 col-sm-6 col-lg-3",
    "items": [[],[],[]],
    "button-icon": {
      "href": "#",
      "icon": "link",
      "text": "Discover More"
    }
  },
  "card-carousel": {
    "title": "Lorem ipsum asi amet",
    "next": {
      "button-icon": {
        "href": "#",
        "icon": "arrow-right8",
        "text": ""
      }
    },
    "prev": {
      "button-icon": {
        "href": "#",
        "icon": "arrow-left8",
        "text": ""
      }
    },
    "items": [[],[],[],[],[],[],[],[],[],[],[],[]]
  },
  "page-header": {
    "image": {
      "1920": "http://placehold.it/1920x1080",
      "1024": "http://placehold.it/1024x576",
      "640": "http://placehold.it/640x360"
    },
    "title": "Lorem ipsum dolor sit amet"
  },
  "jumbotron": {
    "image": false,
    "breadcrumb": true,
    "title": "Lorem ipsum dolor sit amet",
    "text": "Lorem ipsum dolor sit amet, consectetur adipisicing elit. Amet hic placeat enim voluptates voluptas, cumque eaque minus neque culpa. Provident fugiat officia reiciendis possimus, aspernatur rem eum inventore veniam culpa. Lorem ipsum dolor sit amet, consectetur adipisicing elit. Nam perferendis cum nemo corporis rem aliquid. Iste impedit deleniti in, laborum eaque numquam aperiam accusantium consequuntur at reprehenderit! Rem, reiciendis, blanditiis?",
    "cta": {
      "button": {
        "href": "#",
        "text": "Lorem Ipsum dolor",
        "is_anchor": true
      }
    }
  },
  "jumbotron-carousel": {
    "next": {
      "button-icon": {
        "href": "#",
        "icon": "arrow-right8",
        "text": ""
      }
    },
    "prev": {
      "button-icon": {
        "href": "#",
        "icon": "arrow-left8",
        "text": ""
      }
    },
    "items": [
      {
        "jumbotron": {
          "image": {
            "1920": "http://placehold.it/1920x1080",
            "1024": "http://placehold.it/1024x576",
            "640": "http://placehold.it/640x360"
          },
          "breadcrumb": false,
          "title": "I am the title of this page ",
          "text": "I am the subtitle, lorem ipsum dolor sit amet, consectetur adipiscing elit. ",
          "cta": {
            "button": {
              "href": "#",
              "text": "Call to action",
              "is_anchor": true
            }
          }
        }
      },
      {
        "jumbotron": {
          "image": {
            "1920": "http://placehold.it/1920x1080",
            "1024": "http://placehold.it/1024x576",
            "640": "http://placehold.it/640x360"
          },
          "breadcrumb": false,
          "title": "I am the title of this page 2",
          "text": "I am the subtitle, lorem ipsum dolor sit amet, consectetur adipiscing elit. ",
          "cta": {
            "button": {
              "href": "#",
              "text": "Call to action",
              "is_anchor": true
            }
          }
        }
      },
      {
        "jumbotron": {
          "image": {
            "1920": "http://placehold.it/1920x1080",
            "1024": "http://placehold.it/1024x576",
            "640": "http://placehold.it/640x360"
          },
          "breadcrumb": false,
          "title": "I am the title of this page 3",
          "text": "I am the subtitle, lorem ipsum dolor sit amet, consectetur adipiscing elit. ",
          "cta": {
            "button": {
              "href": "#",
              "text": "Call to action",
              "is_anchor": true
            }
          }
        }
      }
    ]
  },
  "product": {
    "href": "#",
    "image": "http://placehold.it/300x445",
    "name": "Lorem ipsum dolor sit amet",
    "price": "12.99 €"
  },
  "product-carousel": {
    "title": "Lorem ipsum asi amet",
    "next": {
      "button-icon": {
        "href": "#",
        "icon": "arrow-right8",
        "text": ""
      }
    },
    "prev": {
      "button-icon": {
        "href": "#",
        "icon": "arrow-left8",
        "text": ""
      }
    },
    "items": [[],[],[],[],[],[],[],[],[],[],[],[]]
  },
  "map": {
    "lat": "42.8835922",
    "lng": "11.3217915",
    "url": "https://goo.gl/maps/iM9J8FV6Y8r",
    "zoom": "9",
    "marker-icon": "../../img/map-marker.svg"
  },
  "caption": "Lorem ipsum dolor sit amet, consectetur adipisicing elit. Eaque ex animi minima quo voluptas consequatur ullam ipsum amet nobis, cum tenetur placeat labore magni odio distinctio rerum nemo iure maxime.",
  "richtext": "<h2>Lorem ipsum dolor sit amet, consectetur adipiscing elit.</h2><p>Lorem ipsum dolor sit amet, consectetur adipiscing elit. Suspendisse posuere neque et eros cursus varius. Mauris interdum leo vitae massa hendrerit, vitae gravida mi congue. Etiam imperdiet non risus sit amet consectetur.</p><h3>Lorem ipsum dolor sit</h3><p>Mauris interdum leo vitae massa hendrerit, vitae gravida mi congue. Etiam imperdiet non risus sit amet consectetur.</p><h3>Nam pulvinar nibh pretium faucibus</h3><p>Suspendisse posuere neque et eros cursus varius. Mauris interdum leo vitae massa hendrerit, vitae gravida mi congue. Etiam imperdiet non risus sit amet consectetur.</p><blockquote>Lorem ipsum dolor sit amet, consectetur adipisicing elit. Officia et, optio quo quasi cupiditate dolorum, eveniet, nihil enim, ipsam officiis voluptate adipisci ex. Consequuntur dolorum facere commodi minus beatae, neque.</blockquote><h2>Lorem ipsum dolor</h2><ul><li><a href=\"#\">Lorem</a></li><li><a href=\"#\">Lorem</a></li><li><a href=\"#\">Lorem</a></li><li><a href=\"#\">Lorem</a></li><li><a href=\"#\">Lorem</a></li><li><a href=\"#\">Lorem</a></li></ul>",
  "filter-form": {
    "title": {
      "input": {
        "type": "text",
        "placeholder": "Title",
        "name": "title",
        "required": false,
        "value": ""
      }
    },
    "discipline": {
      "select": {
        "placeholder": "Discipline",
        "required": false,
        "name": "discipline",
        "options": [{
          "value": "1",
          "text": "Discipline 1"
        }, {
          "value": "2",
          "text": "Discipline 2"
        }, {
          "value": "3",
          "text": "Discipline 3"
        }, {
          "value": "4",
          "text": "Discipline 4"
        }]
      }
    },
    "location": {
      "select": {
        "placeholder": "Location",
        "required": false,
        "name": "location",
        "options": [{
          "value": "1",
          "text": "Location 1"
        }, {
          "value": "2",
          "text": "Location 2"
        }, {
          "value": "3",
          "text": "Location 3"
        }, {
          "value": "4",
          "text": "Location 4"
        }]
      }
    },
    "submit": {
      "button": {
        "is_anchor": false,
        "text": "Filter"
      }
    },
    "more": {
      "button-icon": {
        "icon": "calendar",
        "href": "#"
      }
    }
  },
  "contact-form": {
    "name": {
      "input": {
        "type": "text",
        "placeholder": "Name",
        "name": "name",
        "required": true,
        "value": ""
      }
    },
    "surname": {
      "input": {
        "type": "text",
        "placeholder": "Surname",
        "name": "surname",
        "required": true,
        "value": ""
      }
    },
    "email": {
      "input": {
        "type": "text",
        "placeholder": "Email",
        "name": "email",
        "required": true,
        "value": ""
      }
    },
    "phone": {
      "input": {
        "type": "text",
        "placeholder": "Phone",
        "name": "phone",
        "required": false,
        "value": ""
      }
    },
    "subject": {
      "input": {
        "type": "text",
        "placeholder": "Message Subject",
        "name": "subject",
        "required": false,
        "value": ""
      }
    },
    "branch": {
      "select": {
        "placeholder": "Select Branch",
        "required": false,
        "name": "branch",
        "options": [{
          "value": "1",
          "text": "Branch: Shang Shung Institute UK"
        }, {
          "value": "2",
          "text": "Branch: Shang Shung Institute IT"
        }, {
          "value": "3",
          "text": "Branch: Shang Shung Institute US"
        }, {
          "value": "4",
          "text": "Branch: Shang Shung Institute JP"
        }]
      }
    },
    "privacy": {
      "checkbox": {
        "required": true,
        "name": "privacy",
        "checked": false,
        "text": "Lorem ipsum dolor sit amet, consectetur adipisicing elit. Repellendus beatae ad saepe sapiente minus odit excepturi veritatis quam quae modi sed perferendis nostrum pariatur, dolorem accusantium, illo iste qui blanditiis."
      }
    },
    "message": {
      "textarea": {
        "placeholder": "Enter your message",
        "name": "message",
        "required": true
      }
    },
    "submit": {
      "button": {
        "is_anchor": false,
        "text": "Send Message"
      }
    }
  },
  "newsletter-form": {
    "email": {
      "input": {
        "type": "text",
        "placeholder": "Enter your email",
        "name": "email",
        "required": true,
        "value": ""
      }
    },
    "submit": {
      "button": {
        "is_anchor": false,
        "text": "Sign up"
      }
    }
  }
}
